topsis_nitish_102303239/__init__.py
topsis_nitish_102303239/topsis.py
topsis_nitish_102303239-1.0.0.dist-info/METADATA
topsis_nitish_102303239-1.0.0.dist-info/WHEEL
topsis_nitish_102303239-1.0.0.dist-info/entry_points.txt
topsis_nitish_102303239-1.0.0.dist-info/top_level.txt
topsis_nitish_102303239-1.0.0.dist-info/RECORD
