Metadata-Version: 2.4
Name: Topsis-Nitish-102303239
Version: 1.0.0
Summary: A Python package for implementing TOPSIS (Technique for Order Preference by Similarity to Ideal Solution)
Author: Nitish
Author-email: nitish@example.com
Requires-Dist: pandas
Requires-Dist: numpy
Dynamic: author
Dynamic: author-email
Dynamic: description
Dynamic: description-content-type
Dynamic: requires-dist
Dynamic: summary
